Workbook

Sheet Cover
B2: DIXON TECHNOLOGIES (INDIA) LTD.
B3: 3-Statement Financial Model + FCFF DCF Valuation
B4: NSE: DIXON · BSE: 541988 · EMS / Electronics Manufacturing Services
B6: Analyst | C6: Om Chaudhari — IIT Bombay, B.Tech (Year 2)
B7: Project | C7: WiDS 5.0 Financial Modelling Bootcamp
B8: Date | C8: June 2026
B9: Model Version | C9: v3.0 — Fully Integrated, Single Source
B10: Data Source | C10: Screener.in (Consolidated Financials)
B11: Historical | C11: FY21A – FY26A (6 years)
B12: Forecast | C12: FY27E – FY31E (5 years explicit period)
B13: Currency | C13: ₹ Crore · Indian FY (Apr 1 – Mar 31)
B14: Valuation | C14: FCFF DCF · WACC 13.6% · TGR 5.5%
B16: HISTORICAL SNAPSHOT (₹ Crore, Screener.in)
C17: FY21A | D17: FY22A | E17: FY23A | F17: FY24A | G17: FY25A | H17: FY26A
B18: Revenue | C18: 6448 | D18: 10697 | E18: 12192 | F18: 17691 | G18: 38860 | H18: 48873
B19: EBITDA | C19: 292 | D19: 384 | E19: 519 | F19: 705 | G19: 1515 | H19: 1867
B20: EBITDA % | C20: 0.04528536 | D20: 0.035897915 | E20: 0.042568898 | F20: 0.039850772 | G20: 0.038986104 | H20: 0.038201052
B21: Net Profit | C21: 160 | D21: 190 | E21: 255 | F21: 375 | G21: 1233 | H21: 1644
B22: EPS (₹) | C22: 27.28 | D22: 32.05 | E22: 42.9 | F22: 61.47 | G22: 181.87 | H22: 236.61
B24: COLOUR LEGEND
B25: Blue text | C25: Hardcoded input / assumption
B26: Black text | C26: Excel formula
B27: Green text | C27: Cross-sheet formula link
B28: Grey fill | C28: Subtotal / total row
B30: Disclaimer: Academic exercise. Not investment advice. All data from Screener.in public filings.

Sheet ASSUMP
B1: ASSUMPTIONS — Dixon Technologies v3.0
C2: FY27E | D2: FY28E | E2: FY29E | F2: FY30E | G2: FY31E | H2: Notes | I2: Source
B3: INCOME STATEMENT DRIVERS
B4: Revenue Growth YoY | C4: 0.22 | D4: 0.2 | E4: 0.18 | F4: 0.16 | G4: 0.14 | H4: Moderating from +25.8% FY26A | I4: Company guidance / EMS sector outlook
B5: EBITDA Margin (Operating Profit / Sales) | C5: 0.041 | D5: 0.043 | E5: 0.045 | F5: 0.047 | G5: 0.048 | H5: Screener OP margin 3.9-4.0%; gradual expansion | I5: Screener.in
B6: Other Income as % Revenue | C6: 0.008 | D6: 0.007 | E6: 0.006 | F6: 0.005 | G6: 0.005 | H6: PLI + subsidiary dividends; normalized lower | I6: Screener.in
B7: D&A as % Revenue | C7: 0.0075 | D7: 0.008 | E7: 0.0082 | F7: 0.0083 | G7: 0.0083 | H7: Capex intensification → rising D&A | I7: Screener.in
B8: Tax Rate | C8: 0.22 | H8: Normalized; FY25-26 low due to PLI | I8: Income Tax Act India
B10: BALANCE SHEET DRIVERS — WORKING CAPITAL DAYS
B11: Debtor Days | C11: 50 | H11: FY26A actual: 50 days (₹6,695Cr/₹48,873Cr×365) | I11: Screener.in
B12: Inventory Days | C12: 40 | H12: FY25: 41 days; stable | I12: Screener.in
B13: Days Payable | C13: 105 | H13: FY25: 111 days; slight tightening | I13: Screener.in
B14: COGS as % Revenue (for payables base) | C14: 0.88 | H14: Screener expenses/revenue | I14: Screener.in
B16: CAPEX & DEBT
B17: Capex as % Revenue | C17: 0.028 | D17: 0.026 | E17: 0.024 | F17: 0.022 | G17: 0.02 | H17: FY26A actual: 2.6%; 2.8% for FY27E then declining | I17: Screener.in CF
B18: Pre-tax Cost of Debt (Kd) | C18: 0.085 | H18: Repo rate + ~200bps spread | I18: RBI + estimate
B19: Debt Outstanding (₹ Cr) | C19: 1100 | D19: 1200 | E19: 1300 | F19: 1350 | G19: 1400 | H19: Moderate leverage; EMS asset-light
B21: WACC DERIVATION (CAPM)
B22: Risk-Free Rate (Rf) | C22: 0.07 | H22: India 10-yr G-Sec | I22: RBI June 2026
B23: Equity Risk Premium (ERP) | C23: 0.06 | H23: Damodaran India ERP | I23: Damodaran Jan 2026
B24: Beta (β, levered) | C24: 1.4 | H24: 2-yr weekly vs Nifty 50 | I24: Screener / NSE
B25: Cost of Equity (Ke = Rf + β×ERP) | C25: 0.154 | H25: CAPM | I25: Derived
B26: Pre-tax Cost of Debt (Kd) | C26: 0.085 | H26: Repo + spread | I26: RBI
B27: Tax Rate for WACC | C27: 0.22 | H27: Normalized | I27: Income Tax Act
B28: After-tax Cost of Debt | C28: 0.0663 | H28: Kd × (1-t) | I28: Derived
B29: Debt Weight (D/V) | C29: 0.2 | H29: FY26 BS structure | I29: Screener.in
B30: Equity Weight (E/V) | C30: 0.8 | H30: 1 - D/V | I30: Derived
B31: WACC | C31: 0.13646 | H31: Ke×E% + Kd(at)×D% | I31: Derived
B33: TERMINAL VALUE
B34: Terminal Growth Rate (TGR) | C34: 0.055 | H34: Conservative India nominal GDP proxy | I34: IMF / RBI
B35: Shares Outstanding (Lakh) | C35: 676.4 | H35: FY26 diluted | I35: Screener.in
B38: Colour: Blue = hardcoded input · Black = derived formula · All assumptions editable in this tab only

Sheet IS
A1: INCOME STATEMENT — Dixon Technologies (India) Ltd.
A2: ₹ Crore | C2: FY21 | D2: FY22 | E2: FY23 | F2: FY24 | G2: FY25 | H2: FY26 | I2: FY27E | J2: FY28E | K2: FY29E | L2: FY30E | M2: FY31E
A3: Revenue (Net Sales) | C3: 6448 | D3: 10697 | E3: 12192 | F3: 17691 | G3: 38860 | H3: 48873 | I3: =ROUND(H3*(1+ASSUMP!C4),0) | J3: =ROUND(I3*(1+ASSUMP!D4),0) | K3: =ROUND(J3*(1+ASSUMP!E4),0) | L3: =ROUND(K3*(1+ASSUMP!F4),0) | M3: =ROUND(L3*(1+ASSUMP!G4),0)
A4: YoY Revenue Growth % | D4: =D3/C3-1 | E4: =E3/D3-1 | F4: =F3/E3-1 | G4: =G3/F3-1 | H4: =H3/G3-1 | I4: =ASSUMP!C4 | J4: =ASSUMP!D4 | K4: =ASSUMP!E4 | L4: =ASSUMP!F4 | M4: =ASSUMP!G4
A5: Material Cost | C5: 5479 | D5: 9385 | E5: 10506 | F5: 15457 | G5: 34357 | H5: 43716 | I5: =ROUND(I8*0.92,0) | J5: =ROUND(J8*0.92,0) | K5: =ROUND(K8*0.92,0) | L5: =ROUND(L8*0.92,0) | M5: =ROUND(M8*0.92,0)
A6: Employee Benefit Expenses | C6: 123 | D6: 206 | E6: 233 | F6: 340 | G6: 373 | H6: 470 | I6: =ROUND(I8*0.015,0) | J6: =ROUND(J8*0.015,0) | K6: =ROUND(K8*0.015,0) | L6: =ROUND(L8*0.015,0) | M6: =ROUND(M8*0.015,0)
A7: Other Operating Costs (incl. Mfg., Inventory Δ) | C7: =C8-C5-C6 | D7: =D8-D5-D6 | E7: =E8-E5-E6 | F7: =F8-F5-F6 | G7: =G8-G5-G6 | H7: =H8-H5-H6 | I7: =I8-I5-I6 | J7: =J8-J5-J6 | ... M7: =M8-M5-M6
A8: Total Operating Expenses | C8: =C3-C9 | D8: =D3-D9 | E8: =E3-E9 | F8: =F3-F9 | G8: =G3-G9 | H8: =H3-H9 | I8: =I3-I9 | J8: =J3-J9 | ... M8: =M3-M9
A9: EBITDA (Operating Profit) | C9: 292 | D9: 384 | E9: 519 | F9: 705 | G9: 1515 | H9: 1867 | I9: =ROUND(I3*ASSUMP!C5,0) | J9: =ROUND(J3*ASSUMP!D5,0) | K9: =ROUND(K3*ASSUMP!E5,0) | L9: =ROUND(L3*ASSUMP!F5,0) | M9: =ROUND(M3*ASSUMP!G5,0)
A10: EBITDA Margin % | C10: =C9/C3 | D10: =D9/D3 | E10: =E9/E3 | F10: =F9/F3 | G10: =G9/G3 | H10: =H9/H3 | I10: =I9/I3 | J10: =J9/J3 | ... M10: =M9/M3
A11: Depreciation & Amortisation (D&A) | C11: 44 | D11: 84 | E11: 115 | F11: 162 | G11: 281 | H11: 393 | I11: =ROUND(I3*ASSUMP!C7,0) | J11: =ROUND(J3*ASSUMP!D7,0) | K11: =ROUND(K3*ASSUMP!E7,0) | L11: =ROUND(L3*ASSUMP!F7,0) | M11: =ROUND(M3*ASSUMP!G7,0)
A12: EBIT (Operating Income) | C12: =C9-C11 | D12: =D9-D11 | E12: =E9-E11 | F12: =F9-F11 | G12: =G9-G11 | H12: =H9-H11 | I12: =I9-I11 | J12: =J9-J11 | ... M12: =M9-M11
A13: EBIT Margin % | C13: =C12/C3 | D13: =D12/D3 | E13: =E12/E3 | F13: =F12/F3 | G13: =G12/G3 | H13: =H12/H3 | I13: =I12/I3 | J13: =J12/J3 | ... M13: =M12/M3
A14: Add: Other Income (non-operating) | C14: 1 | D14: 4 | E14: 4 | F14: 32 | G14: 497 | H14: 734 | I14: =ROUND(I3*ASSUMP!C6,0) | J14: =ROUND(J3*ASSUMP!D6,0) | K14: =ROUND(K3*ASSUMP!E6,0) | L14: =ROUND(L3*ASSUMP!F6,0) | M14: =ROUND(M3*ASSUMP!G6,0)
A15: Less: Interest Expense | C15: 33 | D15: 49 | E15: 64 | F15: 81 | G15: 162 | H15: 137 | I15: =ROUND(BS!H10*ASSUMP!C18,0) | J15: =ROUND(BS!I10*ASSUMP!C18,0) | K15: =ROUND(BS!J10*ASSUMP!C18,0) | L15: =ROUND(BS!K10*ASSUMP!C18,0) | M15: =ROUND(BS!L10*ASSUMP!C18,0)
A16: PBT (Profit Before Tax) | C16: =C12+C14-C15 | D16: =D12+D14-D15 | E16: =E12+E14-E15 | F16: =F12+F14-F15 | G16: =G12+G14-G15 | H16: =H12+H14-H15 | I16: =I12+I14-I15 | J16: =J12+J14-J15 | ... M16: =M12+M14-M15
A17: Income Tax | C17: 57 | D17: 65 | E17: 90 | F17: 119 | G17: 337 | H17: 427 | I17: =ROUND(I16*ASSUMP!C8,0) | J17: =ROUND(J16*ASSUMP!C8,0) | K17: =ROUND(K16*ASSUMP!C8,0) | L17: =ROUND(L16*ASSUMP!C8,0) | M17: =ROUND(M16*ASSUMP!C8,0)
A18: PAT (Net Profit) | C18: =C16-C17 | D18: =D16-D17 | E18: =E16-E17 | F18: =F16-F17 | G18: =G16-G17 | H18: =H16-H17 | I18: =I16-I17 | J18: =J16-J17 | ... M18: =M16-M17
A19: PAT Margin % | C19: =C18/C3 | D19: =D18/D3 | E19: =E18/E3 | F19: =F18/F3 | G19: =G18/G3 | H19: =H18/H3 | I19: =I18/I3 | J19: =J18/J3 | ... M19: =M18/M3
A20: EPS (₹ per share) | C20: 27.28 | D20: 32.05 | E20: 42.9 | F20: 61.47 | G20: 181.87 | H20: 236.61 | I20: =ROUND(I18*100/ASSUMP!C35,2) | J20: =ROUND(J18*100/ASSUMP!C35,2) | K20: =ROUND(K18*100/ASSUMP!C35,2) | L20: =ROUND(L18*100/ASSUMP!C35,2) | M20: =ROUND(M18*100/ASSUMP!C35,2)
A21: Dividends Paid | C21: 6 | D21: 11 | E21: 18 | F21: 30 | G21: 49 | H21: 66 | I21: =ROUND(I18*0.05,0) | J21: =ROUND(J18*0.05,0) | K21: =ROUND(K18*0.05,0) | L21: =ROUND(L18*0.05,0) | M21: =ROUND(M18*0.05,0)
A22: Retained Earnings (PAT – Dividends) | C22: 154 | D22: 179 | E22: 237 | F22: 345 | G22: 1184 | H22: 1578 | I22: =I18-I21 | J22: =J18-J21 | K22: =K18-K21 | L22: =L18-L21 | M22: =M18-M21
A24: Depreciation (memo — used in CF) | C24: =C11 | D24: =D11 | E24: =E11 | F24: =F11 | G24: =G11 | H24: =H11 | I24: =I11 | J24: =J11 | ... M24: =M11
A25: NOPAT = EBIT × (1 − Tax) [DCF input] | C25: =ROUND(C12*(1-0.26),0) | D25: =ROUND(D12*(1-0.25),0) | E25: =ROUND(E12*(1-0.26),0) | F25: =ROUND(F12*(1-0.24),0) | G25: =ROUND(G12*(1-0.21),0) | H25: =ROUND(H12*(1-0.21),0) | I25: =ROUND(I12*(1-ASSUMP!C8),0) | J25: =ROUND(J12*(1-ASSUMP!C8),0) | K25: =ROUND(K12*(1-ASSUMP!C8),0) | L25: =ROUND(L12*(1-ASSUMP!C8),0) | M25: =ROUND(M12*(1-ASSUMP!C8),0)

Sheet BS
A1: BALANCE SHEET — Dixon Technologies (India) Ltd.
A2: ₹ Crore | C2: FY21 | D2: FY22 | E2: FY23 | F2: FY24 | G2: FY25 | H2: FY26 | I2: FY27E | J2: FY28E | K2: FY29E | L2: FY30E | M2: FY31E
A3: EQUITY & LIABILITIES
A4: Equity Share Capital | C4: 12 | D4: 12 | E4: 12 | F4: 12 | G4: 12 | H4: 12 | I4: =H4 | J4: =H4 | K4: =H4 | L4: =H4 | M4: =H4
A5: Reserves & Surplus | C5: 726 | D5: 985 | E5: 1273 | F5: 1683 | G5: 2998 | H5: 4665 | I5: =H5+IS!I22 | J5: =I5+IS!J22 | K5: =J5+IS!K22 | L5: =K5+IS!L22 | M5: =L5+IS!M22
A6: Total Shareholders' Equity | C6: =C4+C5 | D6: =D4+D5 | E6: =E4+E5 | F6: =F4+F5 | G6: =G4+G5 | H6: =H4+H5 | I6: =I4+I5 | J6: =J4+J5 | ... M6: =M4+M5
A7: Minority Interest | C7: 50 | D7: 50 | E7: 50 | F7: 50 | G7: 50 | H7: 50 | I7: 50 | J7: 50 | K7: 50 | L7: 50 | M7: 50
A8: Total Equity (incl. MI) | C8: =C6+C7 | D8: =D6+D7 | E8: =E6+E7 | F8: =F6+F7 | G8: =G6+G7 | H8: =H6+H7 | I8: =I6+I7 | J8: =J6+J7 | ... M8: =M6+M7
A10: Borrowings (Total Debt) | C10: 295 | D10: 667 | E10: 453 | F10: 489 | G10: 671 | H10: 994 | I10: 1100 | J10: 1200 | K10: 1300 | L10: 1350 | M10: 1400
A11: Other Non-Current Liabilities | C11: 363 | D11: 523 | E11: 588 | F11: 961 | G11: 2615 | H11: 2698 | I11: =ROUND(H11*1.05,0) | J11: =ROUND(I11*1.05,0) | K11: =ROUND(J11*1.05,0) | L11: =ROUND(K11*1.05,0) | M11: =ROUND(L11*1.05,0)
A12: TOTAL EQUITY & LIABILITIES | C12: =C8+C10+C11+C27 | D12: =D8+D10+D11+D27 | E12: =E8+E10+E11+E27 | F12: =F8+F10+F11+F27 | G12: =G8+G10+G11+G27 | H12: =H8+H10+H11+H27 | I12: =I8+I10+I11+I27 | J12: =J8+J10+J11+J27 | ... M12: =M8+M10+M11+M27
A14: ASSETS
A15: Net Fixed Assets (PP&E) | C15: 550 | D15: 1003 | E15: 1244 | F15: 1996 | G15: 2774 | H15: 4172 | I15: =ROUND(H15+IS!I3*ASSUMP!C17-IS!I11,0) | J15: =ROUND(I15+IS!J3*ASSUMP!D17-IS!J11,0) | K15: =ROUND(J15+IS!K3*ASSUMP!E17-IS!K11,0) | L15: =ROUND(K15+IS!L3*ASSUMP!F17-IS!L11,0) | M15: =ROUND(L15+IS!M3*ASSUMP!G17-IS!M11,0)
A16: Capital Work-in-Progress (CWIP) | C16: 72 | D16: 22 | E16: 120 | F16: 68 | G16: 257 | H16: 571 | I16: =ROUND(IS!I3*ASSUMP!C17*0.10,0) | J16: =ROUND(IS!J3*ASSUMP!D17*0.10,0) | K16: =ROUND(IS!K3*ASSUMP!E17*0.10,0) | L16: =ROUND(IS!L3*ASSUMP!F17*0.10,0) | M16: =ROUND(IS!M3*ASSUMP!G17*0.10,0)
A17: Investments & Other Non-Current Assets | C17: 95 | D17: 141 | E17: 44 | F17: 20 | G17: 536 | H17: 1007 | I17: =ROUND(H17*1.05,0) | J17: =ROUND(I17*1.05,0) | K17: =ROUND(J17*1.05,0) | L17: =ROUND(K17*1.05,0) | M17: =ROUND(L17*1.05,0)
A19: Trade Receivables (Debtor Days) | C19: 883 | D19: 1348 | E19: 1704 | F19: 2326 | G19: 6920 | H19: 6695 | I19: =ROUND(IS!I3*ASSUMP!C11/365,0) | J19: =ROUND(IS!J3*ASSUMP!C11/365,0) | K19: =ROUND(IS!K3*ASSUMP!C11/365,0) | L19: =ROUND(IS!L3*ASSUMP!C11/365,0) | M19: =ROUND(IS!M3*ASSUMP!C11/365,0)
A20: Inventories (Inventory Days) | C20: 707 | D20: 1260 | E20: 1069 | F20: 1890 | G20: 4365 | H20: 5356 | I20: =ROUND(IS!I3*ASSUMP!C12/365,0) | J20: =ROUND(IS!J3*ASSUMP!C12/365,0) | K20: =ROUND(IS!K3*ASSUMP!C12/365,0) | L20: =ROUND(IS!L3*ASSUMP!C12/365,0) | M20: =ROUND(IS!M3*ASSUMP!C12/365,0)
A21: Other Current Assets (advances, prepaid, etc.) | C21: 358 | D21: 355 | E21: 238 | F21: 387 | G21: 1621 | H21: 1046 | I21: =ROUND(H21*1.08,0) | J21: =ROUND(I21*1.08,0) | K21: =ROUND(J21*1.08,0) | L21: =ROUND(K21*1.08,0) | M21: =ROUND(L21*1.08,0)
A22: Cash & Cash Equivalents (from CF) | C22: 180 | D22: 148 | E22: 261 | F22: 302 | G22: 285 | H22: 315 | I22: =H22+CF!I22 | J22: =I22+CF!J22 | K22: =J22+CF!K22 | L22: =K22+CF!L22 | M22: =L22+CF!M22
A23: Total Current Assets | C23: =C19+C20+C21+C22 | D23: =D19+D20+D21+D22 | E23: =E19+E20+E21+E22 | F23: =F19+F20+F21+F22 | G23: =G19+G20+G21+G22 | H23: =H19+H20+H21+H22 | I23: =I19+I20+I21+I22 | J23: =J19+J20+J21+J22 | ... M23: =M19+M20+M21+M22
A25: Trade Payables (Days Payable) | C25: 1399 | D25: 2218 | E25: 2381 | F25: 3924 | G25: 10400 | H25: 10605 | I25: =ROUND(IS!I3*ASSUMP!C14*ASSUMP!C13/365,0) | J25: =ROUND(IS!J3*ASSUMP!C14*ASSUMP!C13/365,0) | K25: =ROUND(IS!K3*ASSUMP!C14*ASSUMP!C13/365,0) | L25: =ROUND(IS!L3*ASSUMP!C14*ASSUMP!C13/365,0) | M25: =ROUND(IS!M3*ASSUMP!C14*ASSUMP!C13/365,0)
A26: Other Current Liabilities (accruals, advances) | C26: 52 | D26: 50 | E26: 50 | F26: 50 | G26: 62 | H26: 188 | I26: =ROUND(H26*1.10,0) | J26: =ROUND(I26*1.10,0) | K26: =ROUND(J26*1.10,0) | L26: =ROUND(K26*1.10,0) | M26: =ROUND(L26*1.10,0)
A27: Total Current Liabilities | C27: =C25+C26 | D27: =D25+D26 | E27: =E25+E26 | F27: =F25+F26 | G27: =G25+G26 | H27: =H25+H26 | I27: =I25+I26 | J27: =J25+J26 | ... M27: =M25+M26
A29: Net Working Capital (CA − CL) | C29: =C23-C27 | D29: =D23-D27 | E29: =E23-E27 | F29: =F23-F27 | G29: =G23-G27 | H29: =H23-H27 | I29: =I23-I27 | J29: =J23-J27 | ... M29: =M23-M27
A30: TOTAL ASSETS | C30: =C15+C16+C17+C23 | D30: =D15+D16+D17+D23 | E30: =E15+E16+E17+E23 | F30: =F15+F16+F17+F23 | G30: =G15+G16+G17+G23 | H30: =H15+H16+H17+H23 | I30: =I15+I16+I17+I23 | J30: =J15+J16+J17+J23 | ... M30: =M15+M16+M17+M23
A32: ✔ BALANCE CHECK (Assets − L&E) = 0 | C32: =C30-C12 | D32: =D30-D12 | E32: =E30-E12 | F32: =F30-F12 | G32: =G30-G12 | H32: =H30-H12 | I32: =I30-I12 | J32: =J30-J12 | ... M32: =M30-M12

Sheet CF
A1: CASH FLOW STATEMENT — Dixon Technologies (India) Ltd.
A2: ₹ Crore | C2: FY21 | D2: FY22 | E2: FY23 | F2: FY24 | G2: FY25 | H2: FY26 | I2: FY27E | J2: FY28E | K2: FY29E | L2: FY30E | M2: FY31E
A3: A. CASH FLOW FROM OPERATING ACTIVITIES
A4: Net Profit (PAT) | C4: 160 | D4: 190 | E4: 255 | F4: 375 | G4: 1233 | H4: 1644 | I4: =IS!I18 | J4: =IS!J18 | K4: =IS!K18 | L4: =IS!L18 | M4: =IS!M18
A5: Add: Depreciation & Amortisation | C5: 44 | D5: 84 | E5: 115 | F5: 162 | G5: 281 | H5: 393 | I5: =IS!I24 | J5: =IS!J24 | K5: =IS!K24 | L5: =IS!L24 | M5: =IS!M24
A6: Add: Interest Expense (reclassified to CFF) | C6: 33 | D6: 49 | E6: 64 | F6: 81 | G6: 162 | H6: 137 | I6: =IS!I15 | J6: =IS!J15 | K6: =IS!K15 | L6: =IS!L15 | M6: =IS!M15
A7: Δ Working Capital [= −(NWC[t]−NWC[t−1]); from BS] | C7: -67 | D7: -50 | E7: 292 | F7: -34 | G7: -526 | H7: -392 | I7: =-((BS!I19+BS!I20+BS!I21-BS!I25-BS!I26)-(BS!H19+BS!H20+BS!H21-BS!H25-BS!H26)) | J7: =-((BS!J19+BS!J20+BS!J21-BS!J25-BS!J26)-(BS!I19+BS!I20+BS!I21-BS!I25-BS!I26)) | K7: =-((BS!K19+BS!K20+BS!K21-BS!K25-BS!K26)-(BS!J19+BS!J20+BS!J21-BS!J25-BS!J26)) | L7: =-((BS!L19+BS!L20+BS!L21-BS!L25-BS!L26)-(BS!K19+BS!K20+BS!K21-BS!K25-BS!K26)) | M7: =-((BS!M19+BS!M20+BS!M21-BS!M25-BS!M26)-(BS!L19+BS!L20+BS!L21-BS!L25-BS!L26))
A8: Other Operating Adjustments (tax, misc) | C8: 0 | D8: 0 | E8: 0 | F8: 0 | G8: 0 | H8: 0 | I8: =0 | J8: =0 | K8: =0 | L8: =0 | M8: =0
A9: Cash Flow from Operations (CFO) | C9: 170 | D9: 273 | E9: 726 | F9: 584 | G9: 1150 | H9: 1782 | I9: =I4+I5+I6+I7+I8 | J9: =J4+J5+J6+J7+J8 | K9: =K4+K5+K6+K7+K8 | L9: =L4+L5+L6+L7+L8 | M9: =M4+M5+M6+M7+M8
A11: B. CASH FLOW FROM INVESTING ACTIVITIES
A12: Capital Expenditure (Capex) | C12: -265 | D12: -464 | E12: -356 | F12: -531 | G12: -1093 | H12: -1251 | I12: =-ROUND(IS!I3*ASSUMP!C17,0) | J12: =-ROUND(IS!J3*ASSUMP!D17,0) | K12: =-ROUND(IS!K3*ASSUMP!E17,0) | L12: =-ROUND(IS!L3*ASSUMP!F17,0) | M12: =-ROUND(IS!M3*ASSUMP!G17,0)
A13: Net Investment Activity (acquisitions etc.) | C13: 0 | D13: 0 | E13: 0 | F13: 0 | G13: 0 | H13: 0 | I13: =0 | J13: =0 | K13: =0 | L13: =0 | M13: =0
A14: Cash Flow from Investing (CFI) | C14: -265 | D14: -464 | E14: -356 | F14: -531 | G14: -1093 | H14: -1251 | I14: =I12+I13 | J14: =J12+J13 | K14: =K12+K13 | L14: =L12+L13 | M14: =M12+M13
A16: C. CASH FLOW FROM FINANCING ACTIVITIES
A17: Net Borrowings / (Repayments) | C17: 0 | D17: 372 | E17: -214 | F17: 36 | G17: 182 | H17: 323 | I17: =BS!I10-BS!H10 | J17: =BS!J10-BS!I10 | K17: =BS!K10-BS!J10 | L17: =BS!L10-BS!K10 | M17: =BS!M10-BS!L10
A18: Dividends Paid | C18: -6 | D18: -11 | E18: -18 | F18: -30 | G18: -49 | H18: -66 | I18: =-IS!I21 | J18: =-IS!J21 | K18: =-IS!K21 | L18: =-IS!L21 | M18: =-IS!M21
A19: Interest Paid | C19: -33 | D19: -49 | E19: -64 | F19: -81 | G19: -162 | H19: -137 | I19: =-IS!I15 | J19: =-IS!J15 | K19: =-IS!K15 | L19: =-IS!L15 | M19: =-IS!M15
A20: Cash Flow from Financing (CFF) | C20: 63 | D20: 304 | E20: -330 | F20: -70 | G20: -27 | H20: -108 | I20: =I17+I18+I19 | J20: =J17+J18+J19 | K20: =K17+K18+K19 | L20: =L17+L18+L19 | M20: =M17+M18+M19
A22: NET CHANGE IN CASH (A + B + C) | C22: -32 | D22: 113 | E22: 41 | F22: -17 | G22: 30 | H22: 424 | I22: =I9+I14+I20 | J22: =J9+J14+J20 | K22: =K9+K14+K20 | L22: =L9+L14+L20 | M22: =M9+M14+M20
A23: Opening Cash Balance | C23: 180 | D23: 148 | E23: 261 | F23: 302 | G23: 285 | H23: 315 | I23: =BS!H22 | J23: =BS!I22 | K23: =BS!J22 | L23: =BS!K22 | M23: =BS!L22
A24: Closing Cash [= BS Cash — integration check] | C24: =C23+C22 | D24: =D23+D22 | E24: =E23+E22 | F24: =F23+F22 | G24: =G23+G22 | H24: =H23+H22 | I24: =I23+I22 | J24: =J23+J22 | ... M24: =M23+M22

Sheet DCF
A1: DCF VALUATION — Dixon Technologies (India) Ltd. (FCFF Method)
A2: WACC | C2: =ASSUMP!C31
A3: Terminal Growth Rate | C3: =ASSUMP!C34
A4: Shares (Lakh) | C4: =ASSUMP!C35
A6: FCFF BRIDGE (Forecast Years FY27E–FY31E)
A7: ₹ Crore | C7: FY27E | D7: FY28E | E7: FY29E | F7: FY30E | G7: FY31E
A8: Revenue | C8: =IS!I3 | D8: =IS!J3 | E8: =IS!K3 | F8: =IS!L3 | G8: =IS!M3
A9: NOPAT (= EBIT × (1−t)) | C9: =IS!I25 | D9: =IS!J25 | E9: =IS!K25 | F9: =IS!L25 | G9: =IS!M25
A10: Add: Depreciation & Amortisation | C10: =IS!I24 | D10: =IS!J24 | E10: =IS!K24 | F10: =IS!L24 | G10: =IS!M24
A11: Less: Capex | C11: =-CF!I12 | D11: =-CF!J12 | E11: =-CF!K12 | F11: =-CF!L12 | G11: =-CF!M12
A12: Less/Add: Δ Working Capital [from BS] | C12: =CF!I7 | D12: =CF!J7 | E12: =CF!K7 | F12: =CF!L7 | G12: =CF!M7
A13: FREE CASH FLOW TO FIRM (FCFF) | C13: =C9+C10-C11+C12 | D13: =D9+D10-D11+D12 | E13: =E9+E10-E11+E12 | F13: =F9+F10-F11+F12 | G13: =G9+G10-G11+G12
A14: Discount Period (mid-year) | C14: 0.5 | D14: 1.5 | E14: 2.5 | F14: 3.5 | G14: 4.5
A15: Discount Factor [1/(1+WACC)^n] | C15: =1/(1+ASSUMP!C31)^C14 | D15: =1/(1+ASSUMP!C31)^D14 | E15: =1/(1+ASSUMP!C31)^E14 | F15: =1/(1+ASSUMP!C31)^F14 | G15: =1/(1+ASSUMP!C31)^G14
A16: PV of FCFF | C16: =C13*C15 | D16: =D13*D15 | E16: =E13*E15 | F16: =F13*F15 | G16: =G13*G15
A18: TERMINAL VALUE (Gordon Growth)
A19: Terminal FCFF = FCFF_FY31E × (1+TGR) | C19: =G13*(1+ASSUMP!C34)
A20: Terminal Value = Terminal FCFF / (WACC − TGR) | C20: =C19/(ASSUMP!C31-ASSUMP!C34)
A21: TV Discount Period | C21: 5
A22: PV of Terminal Value | C22: =C20/(1+ASSUMP!C31)^C21
A24: ENTERPRISE VALUE BRIDGE → EQUITY VALUE → PRICE
A25: Sum of PV(FCFF) FY27E–FY31E | C25: =SUM(C16:G16)
A26: Add: PV of Terminal Value | C26: =C22
A27: ENTERPRISE VALUE (EV) | C27: =C25+C26
A29: Less: Total Debt (FY26A) | C29: =-(BS!H10)
A30: Add: Cash & Equivalents (FY26A) | C30: =BS!H22
A31: Less: Minority Interest (FY26A) | C31: =-(BS!H7)
A32: EQUITY VALUE (₹ Crore) | C32: =C27+C29+C30+C31
A34: Shares Outstanding (Lakh) | C34: =ASSUMP!C35
A35: IMPLIED SHARE PRICE (₹ / share) | C35: =ROUND(C32*100/C34,0)
A37: Current Market Price (₹) [manual input] | C37: 13000
A38: Upside / (Downside) % | C38: =C35/C37-1

Sheet SENSITIVITY
A1: SENSITIVITY ANALYSIS — Implied Share Price (₹) vs WACC × TGR
A3: WACC ↓ / TGR → | B3: 4.0% | C3: 4.5% | D3: 5.0% | E3: 5.5% | F3: 6.0% | G3: 6.5% | H3: 7.0%
A4: 11.0% | B4: 3407 | C4: 3641 | D4: 3914 | E4: 4237 | F4: 4624 | G4: 5098 | H4: 5689
A5: 12.0% | B5: 2923 | C5: 3095 | D5: 3290 | E5: 3516 | F5: 3780 | G5: 4091 | H5: 4465
A6: 12.5% | B6: 2725 | C6: 2874 | D6: 3042 | E6: 3234 | F6: 3456 | G6: 3715 | H6: 4021
A7: 13.0% | B7: 2549 | C7: 2679 | D7: 2825 | E7: 2990 | F7: 3179 | G7: 3397 | H7: 3651
A8: 13.6% | B8: 2363 | C8: 2474 | D8: 2598 | E8: 2738 | F8: 2896 | G8: 3076 | H8: 3283
A9: 14.0% | B9: 2252 | C9: 2353 | D9: 2465 | E9: 2590 | F9: 2731 | G9: 2890 | H9: 3073
A10: 15.0% | B10: 2010 | C10: 2090 | D10: 2178 | E10: 2275 | F10: 2383 | G10: 2504 | H10: 2640
A11: 16.0% | B11: 1809 | C11: 1874 | D11: 1944 | E11: 2022 | F11: 2107 | G11: 2201 | H11: 2305
A14: Note: Highlighted cell = base-case WACC/TGR. Values computed using forecast FCFF from ASSUMP assumptions.

Sheet COMPS
A1: PEER COMPARABLES — EMS / Electronics Sector (India)
A2: Company | B2: NSE Ticker | C2: Mkt Cap (₹Cr) | D2: Revenue (₹Cr) | E2: EBITDA% | F2: PAT Margin% | G2: P/E (FY26) | H2: EV/EBITDA | I2: ROCE% | J2: Notes
A3: Dixon Technologies | B3: DIXON | C3: 88,000 | D3: 48,873 | E3: 3.8% | F3: 3.4% | G3: 55x | H3: 45x | I3: 40% | J3: Subject company
A4: Amber Enterprises | B4: AMBER | C4: 18,500 | D4: 7,800 | E4: 5.2% | F4: 2.1% | G4: 58x | H4: 38x | I4: 18% | J4: AC/RAC components
A5: Kaynes Technology | B5: KAYNES | C5: 22,000 | D5: 2,800 | E5: 14.5% | F5: 9.5% | G5: 95x | H5: 65x | I5: 22% | J5: Embedded electronics
A6: Syrma SGS | B6: SYRMA | C6: 7,200 | D6: 3,100 | E6: 6.8% | F6: 3.9% | G6: 62x | H6: 30x | I6: 15% | J6: PCB assemblies
A7: Avalon Technologies | B7: AVALON | C7: 3,500 | D7: 1,500 | E7: 7.5% | F7: 5.0% | G7: 45x | H7: 25x | I7: 19% | J7: Smart meters / EMS
A8: PG Electroplast | B8: PGEL | C8: 9,800 | D8: 5,200 | E8: 5.0% | F8: 3.2% | G8: 70x | H8: 35x | I8: 25% | J8: AC/washing machine
A11: Disclaimer: Peer data sourced from Screener.in public financials & market data (June 2026). For academic reference only. Subject company financials are model-derived.
